CHANGELOG.txt
LICENCE.txt
MANIFEST.in
README.txt
setup.py
CalculadoraInterfaces/MainCalculatorConsole.spec
CalculadoraInterfaces/__init__.py
CalculadoraInterfaces.egg-info/PKG-INFO
CalculadoraInterfaces.egg-info/SOURCES.txt
CalculadoraInterfaces.egg-info/dependency_links.txt
CalculadoraInterfaces.egg-info/top_level.txt
CalculadoraInterfaces/__pycache__/CalculatorDivision.cpython-37.pyc
CalculadoraInterfaces/__pycache__/CalculatorMultiplicar.cpython-37.pyc
CalculadoraInterfaces/__pycache__/CalculatorResta.cpython-37.pyc
CalculadoraInterfaces/__pycache__/CalculatorSuma.cpython-37.pyc
CalculadoraInterfaces/__pycache__/MainCalculatorConsole.cpython-37.pyc
CalculadoraInterfaces/build/MainCalculatorConsole/Analysis-00.toc
CalculadoraInterfaces/build/MainCalculatorConsole/EXE-00.toc
CalculadoraInterfaces/build/MainCalculatorConsole/MainCalculatorConsole.exe.manifest
CalculadoraInterfaces/build/MainCalculatorConsole/PKG-00.toc
CalculadoraInterfaces/build/MainCalculatorConsole/PYZ-00.pyz
CalculadoraInterfaces/build/MainCalculatorConsole/PYZ-00.toc
CalculadoraInterfaces/build/MainCalculatorConsole/Tree-00.toc
CalculadoraInterfaces/build/MainCalculatorConsole/Tree-01.toc
CalculadoraInterfaces/build/MainCalculatorConsole/base_library.zip
CalculadoraInterfaces/build/MainCalculatorConsole/warn-MainCalculatorConsole.txt
CalculadoraInterfaces/build/MainCalculatorConsole/xref-MainCalculatorConsole.html
CalculadoraInterfaces/dist/MainCalculatorConsole.exe
aribasiccalculator.egg-info/SOURCES.txt
aribasiccalculator.egg-info/dependency_links.txt
aribasiccalculator.egg-info/top_level.txt