Metadata-Version: 1.1
Name: CalculadoraInterfaces
Version: 0.0.1
Summary: Operaciones de 2 digitos con Interfaz
Home-page: UNKNOWN
Author: Ari Bautista
Author-email: aribautista66@gmail.com
License: MIT
Keywords: calculator
Platform: UNKNOWN
Classifier: Development Status :: 5 - Production/Stable
Classifier: Intended Audience :: Education
Classifier: Operating System :: Microsoft :: Windows :: Windows 10
Classifier: License :: OSI Approved :: MIT License
Classifier: Programming Language :: Python :: 3
